topsis_calci/__init__.py
topsis_calci/cli.py
topsis_calci/topsis.py
topsis_calci/validators.py
topsis_calci-0.4.dist-info/entry_points.txt
topsis_calci-0.4.dist-info/LICENSE.txt
topsis_calci-0.4.dist-info/WHEEL
topsis_calci-0.4.dist-info/METADATA
topsis_calci-0.4.dist-info/RECORD
