Metadata-Version: 2.1
Name: topsis-calci
Version: 0.4
Summary: 
Home-page: https://github.com/ritikrajdev/topsic-calci
Author: ritikrajdev
Author-email: ritikrajdev761@gmail.com
Requires-Python: >=3.10,<4.0
Classifier: Programming Language :: Python :: 3
Classifier: Programming Language :: Python :: 3.10
Requires-Dist: click (>=8.0.4,<9.0.0)
Requires-Dist: numpy (>=1.22.2,<2.0.0)
Requires-Dist: openpyxl (>=3.0.9,<4.0.0)
Requires-Dist: pandas (>=1.4.1,<2.0.0)
Project-URL: Repository, https://github.com/ritikrajdev/topsic-calci
